src/cleanbug.py
src/configs.py
src/main.py
cleanbug-0.0.1.dist-info/METADATA
cleanbug-0.0.1.dist-info/WHEEL
cleanbug-0.0.1.dist-info/entry_points.txt
cleanbug-0.0.1.dist-info/licenses/LICENSE
cleanbug-0.0.1.dist-info/RECORD
