Metadata-Version: 2.1
Name: cleanbug
Version: 0.0.1
Summary: CLI tool for managing and easily swapping between different versions of code by converting the code into comments and vice versa.
Project-URL: Homepage, https://github.com/SamJohn04/terminal-styler
Project-URL: Bug Tracker, https://github.com/SamJohn04/terminal-styler/issues
Author-email: Samuel John <samuel.john.codes@gmail.com>
License-File: LICENSE
Classifier: License :: OSI Approved :: MIT License
Classifier: Operating System :: OS Independent
Classifier: Programming Language :: Python :: 3
Requires-Python: >=3.7
